LICENSE
README.rst
setup.py
guardian_sdk/Client.py
guardian_sdk/Request.py
guardian_sdk/Response.py
guardian_sdk/__init__.py
guardian_sdk/sample.py
guardian_sdk.egg-info/PKG-INFO
guardian_sdk.egg-info/SOURCES.txt
guardian_sdk.egg-info/dependency_links.txt
guardian_sdk.egg-info/top_level.txt
guardian_sdk/common/__init__.py
guardian_sdk/common/constant.py
guardian_sdk/util/__init__.py
guardian_sdk/util/hmac256.py
guardian_sdk/util/http_util.py
guardian_sdk/util/md5.py
guardian_sdk/util/sign_builder.py
guardian_sdk/util/utils.py